LICENSE
README.md
setup.cfg
setup.py
kano/__init__.py
kano/const/__init__.py
kano/data/__init__.py
kano/data/dataset.py
kano/data/iterate.py
kano/data/loaddata.py
kano/data/timestamp.py
kano/ensemble/__init__.py
kano/ensemble/dean.py
kano/ensemble/densedrop.py
kano/ensemble/genmat.py
kano/ensemble/randnet.py
kano/helper/__init__.py
kano/helper/helper.py
kano/iter/__init__.py
kano/iter/handler.py
kano/iter/helper.py
kano/iter/iterators.py
kano/logging/__init__.py
kano/logging/logger.py
kano/quick/__init__.py
kano/quick/qcardio.py
kano/stats/__init__.py
kano/stats/likelihood.py
kano/stats/methods.py
kano/stats/stats.py
kano/symbols/__init__.py
kano/symbols/metalogic.py
kano/symbols/symbols.py
kano/utils/__init__.py
kano/utils/modify.py
kano/utils/utils.py
kano/vis/__init__.py
kano/vis/altitude.py
kano/vis/hist.py
kano/vis/linedraw.py
kano/vis/projector.py
kano/vis/reducedraw.py
kyano.egg-info/PKG-INFO
kyano.egg-info/SOURCES.txt
kyano.egg-info/dependency_links.txt
kyano.egg-info/requires.txt
kyano.egg-info/top_level.txt