Metadata-Version: 2.1
Name: kyano
Version: 0.7
Summary: Python module providing anomaly detection datasets and tools for evaluating algorithms. Modification of yano, mostly by replacing the datasets, through a kaggle query
Home-page: https://github.com/psorus/kano
Download-URL: https://github.com/psorus/kano/archive/v_01.tar.gz
Author: Simon Klüttermann
Author-email: Simon.Kluettermann@cs.tu-dortmund.de
License: apache-2.0
Keywords: DATA,ANOMALY DETECTION,OUTLIER DETECTION,ML
Platform: UNKNOWN
Classifier: Development Status :: 3 - Alpha
Classifier: Intended Audience :: Science/Research
Classifier: Topic :: Software Development :: Build Tools
Classifier: License :: OSI Approved :: Apache Software License
Classifier: Programming Language :: Python :: 3
Classifier: Programming Language :: Python :: 3.6
Classifier: Programming Language :: Python :: 3.7
Classifier: Programming Language :: Python :: 3.8
Classifier: Programming Language :: Python :: 3.9
Classifier: Programming Language :: Python :: 3.10
License-File: LICENSE
